proxalgs
