Metadata-Version: 1.1
Name: proxalgs
Version: 0.2.4
Summary: Proximal algorithms in python
Home-page: https://github.com/ganguli-lab/proxalgs
Author: Niru Maheshwaranathan
Author-email: nirum@stanford.edu
License: MIT
Platform: UNKNOWN
Classifier: Intended Audience :: Science/Research
Classifier: Operating System :: MacOS :: MacOS X
Classifier: Topic :: Scientific/Engineering :: Information Analysis
